chimera/__init__.py
chimera/__main__.py
chimera/diffusion.py
chimera/dists.py
chimera/model.py
chimera/society.py
chimera/utils.py
chimera/version.py
zf_chimera-0.0.2.dist-info/LICENSE
zf_chimera-0.0.2.dist-info/METADATA
zf_chimera-0.0.2.dist-info/WHEEL
zf_chimera-0.0.2.dist-info/entry_points.txt
zf_chimera-0.0.2.dist-info/top_level.txt
zf_chimera-0.0.2.dist-info/RECORD
