Metadata-Version: 2.1
Name: zf-chimera
Version: 0.0.2
Summary: chimera simulates the diffusion of innovations in a society
Author: zeffmuks
Author-email: zeffmuks@gmail.com
License-File: LICENSE
Requires-Dist: wheel
Requires-Dist: contourpy
Requires-Dist: cycler
Requires-Dist: fonttools
Requires-Dist: Jinja2
Requires-Dist: kiwisolver
Requires-Dist: MarkupSafe
Requires-Dist: matplotlib
Requires-Dist: mpld3
Requires-Dist: networkx
Requires-Dist: numpy
Requires-Dist: packaging
Requires-Dist: pillow
Requires-Dist: pyparsing
Requires-Dist: python-dateutil
Requires-Dist: scipy
Requires-Dist: six
